setup.py
flashcard/__init__.py
flashcard/main.py
flashcard/property.py
flashcard/sources.py
flashcard.egg-info/PKG-INFO
flashcard.egg-info/SOURCES.txt
flashcard.egg-info/dependency_links.txt
flashcard.egg-info/entry_points.txt
flashcard.egg-info/requires.txt
flashcard.egg-info/top_level.txt