Metadata-Version: 1.1
Name: flashcard
Version: 0.0.2
Summary: Simple flashcard in your terminal.
Home-page: https://github.com/sotetsuk/flashcard
Author: sotetsuk
Author-email: sotetsu.koyamada@gmail.com
License: MIT
Platform: UNKNOWN
Classifier: Programming Language :: Python :: 3.2
Classifier: Programming Language :: Python :: 3.3
Classifier: Programming Language :: Python :: 3.4
Classifier: Programming Language :: Python :: 3.5
Classifier: License :: OSI Approved :: MIT License
